setup.py
django_osmp.egg-info/PKG-INFO
django_osmp.egg-info/SOURCES.txt
django_osmp.egg-info/dependency_links.txt
django_osmp.egg-info/not-zip-safe
django_osmp.egg-info/top_level.txt
osmp/__init__.py
osmp/models.py
osmp/utils.py
osmp/views.py
osmp/migrations/0001_initial.py
osmp/migrations/0002_auto_20150713_1227.py
osmp/migrations/0003_auto_20150713_1250.py
osmp/migrations/__init__.py
osmp/south_migrations/0001_initial.py
osmp/south_migrations/0002_auto__add_field_osmp_method.py
osmp/south_migrations/0003_auto__chg_field_osmp_txn_date.py
osmp/south_migrations/0004_auto__add_field_osmp_added.py
osmp/south_migrations/0005_auto__chg_field_osmp_txn_id.py
osmp/south_migrations/__init__.py