Metadata-Version: 1.1
Name: django-osmp
Version: 0.3.1
Summary: OSMP(Qiwi) Interface support for Django.
Home-page: https://github.com/gen1us2k/django-osmp.git
Author: Andrew Minkin
Author-email: minkin.andrew@gmail.com
License: UNKNOWN
Platform: UNKNOWN
Classifier: Development Status :: 3 - Alpha
Classifier: Environment :: Web Environment
Classifier: Intended Audience :: Developers
Classifier: License :: OSI Approved :: MIT License
Classifier: Operating System :: OS Independent
Classifier: Programming Language :: Python
Classifier: Framework :: Django
